unicef_rest_export/__init__.py
unicef_rest_export/renderers.py
unicef_rest_export/serializers.py
unicef_rest_export/views.py
unicef_rest_export/templates/rest_export.html
unicef_rest_export-0.6.dist-info/LICENSE
unicef_rest_export-0.6.dist-info/METADATA
unicef_rest_export-0.6.dist-info/WHEEL
unicef_rest_export-0.6.dist-info/top_level.txt
unicef_rest_export-0.6.dist-info/RECORD
