Metadata-Version: 2.1
Name: unicef-rest-export
Version: 0.6
Summary: Django package that handles exporting of data
Home-page: https://github.com/unicef/unicef-rest-export
Author: UNICEF
Author-email: dev@unicef.org
License: Apache 2 License
Platform: any
Classifier: Environment :: Web Environment
Classifier: Programming Language :: Python :: 3.9
Classifier: Framework :: Django
Classifier: Framework :: Django :: 3.2
Classifier: Framework :: Django :: 4.0
Classifier: Intended Audience :: Developers
License-File: LICENSE
Requires-Dist: django
Requires-Dist: djangorestframework-csv
Requires-Dist: djangorestframework
Requires-Dist: lxml
Requires-Dist: python-docx
Requires-Dist: pytz
Requires-Dist: pyyaml
Requires-Dist: reportlab
Requires-Dist: tablib[html,xls,xlsx]
Requires-Dist: xlrd
Requires-Dist: xlwt
Provides-Extra: test
Requires-Dist: coverage ; extra == 'test'
Requires-Dist: factory-boy ; extra == 'test'
Requires-Dist: faker ; extra == 'test'
Requires-Dist: flake8 ; extra == 'test'
Requires-Dist: isort ; extra == 'test'
Requires-Dist: pytest-cov ; extra == 'test'
Requires-Dist: pytest-django ; extra == 'test'
Requires-Dist: pytest-echo ; extra == 'test'
Requires-Dist: pytest-pythonpath ; extra == 'test'
Requires-Dist: pytest ; extra == 'test'
Requires-Dist: psycopg2 ; extra == 'test'
